beekeeper/embeddings/huggingface/__init__.py
beekeeper/embeddings/huggingface/base.py
beekeeper_embeddings_huggingface-1.0.3.dist-info/METADATA
beekeeper_embeddings_huggingface-1.0.3.dist-info/WHEEL
beekeeper_embeddings_huggingface-1.0.3.dist-info/RECORD
