Metadata-Version: 2.4
Name: beekeeper-embeddings-huggingface
Version: 1.0.3
Summary: beekeeper embeddings huggingface extension
Author-email: Leonardo Furnielis <leonardofurnielis@outlook.com>
License: Apache-2.0
Requires-Python: <4.0,>=3.10
Requires-Dist: beekeeper-core<2.0.0,>=1.0.3
Requires-Dist: sentence-transformers<5.0.0,>=4.1.0
Provides-Extra: dev
Requires-Dist: ruff>=0.11.13; extra == 'dev'
